bigocheck/__init__.py
bigocheck/alerts.py
bigocheck/amortized.py
bigocheck/assertions.py
bigocheck/ast_analysis.py
bigocheck/async_bench.py
bigocheck/badges.py
bigocheck/bounds.py
bigocheck/cases.py
bigocheck/cli.py
bigocheck/cloud.py
bigocheck/compare.py
bigocheck/core.py
bigocheck/dashboard.py
bigocheck/datagen.py
bigocheck/docgen.py
bigocheck/explanations.py
bigocheck/export.py
bigocheck/git_tracking.py
bigocheck/html_report.py
bigocheck/interactive.py
bigocheck/jupyter.py
bigocheck/multi_compare.py
bigocheck/parallel.py
bigocheck/plotting.py
bigocheck/polynomial.py
bigocheck/pre_commit.py
bigocheck/profiles.py
bigocheck/pytest_plugin.py
bigocheck/recommendations.py
bigocheck/regression.py
bigocheck/reports.py
bigocheck/stability.py
bigocheck/statistics.py
bigocheck-0.8.0.dist-info/licenses/LICENSE
bigocheck-0.8.0.dist-info/METADATA
bigocheck-0.8.0.dist-info/WHEEL
bigocheck-0.8.0.dist-info/entry_points.txt
bigocheck-0.8.0.dist-info/top_level.txt
bigocheck-0.8.0.dist-info/RECORD
