Metadata-Version: 2.4
Name: bigocheck
Version: 0.8.0
Summary: Zero-dependency, AI-assisted Big-O complexity checker. Static analysis + empirical benchmarking for Python.
Author: gadwant
License: MIT
Project-URL: Homepage, https://github.com/adwantg/bigocheck
Project-URL: Repository, https://github.com/adwantg/bigocheck
Project-URL: Issues, https://github.com/adwantg/bigocheck/issues
Keywords: complexity,big-o,benchmark,algorithm,static-analysis,ast,profiling,time-complexity,space-complexity,zero-dependency,performance-testing,ai-for-code,developer-tools
Classifier: Development Status :: 5 - Production/Stable
Classifier: Environment :: Console
Classifier: Intended Audience :: Developers
Classifier: Intended Audience :: Science/Research
Classifier: License :: OSI Approved :: MIT License
Classifier: Operating System :: OS Independent
Classifier: Programming Language :: Python :: 3
Classifier: Programming Language :: Python :: 3.9
Classifier: Programming Language :: Python :: 3.10
Classifier: Programming Language :: Python :: 3.11
Classifier: Programming Language :: Python :: 3.12
Classifier: Programming Language :: Python :: 3.13
Classifier: Topic :: Software Development :: Testing
Classifier: Topic :: Software Development :: Libraries :: Python Modules
Classifier: Topic :: System :: Benchmark
Classifier: Typing :: Typed
Requires-Python: >=3.9
License-File: LICENSE
Provides-Extra: dev
Requires-Dist: pytest>=7.0; extra == "dev"
Provides-Extra: plot
Requires-Dist: matplotlib>=3.5; extra == "plot"
Dynamic: license-file
